Workbook

Sheet Dashboard
A1: GESTAO FINANCEIRA — RE9 IMOB
A2: Atualizado automaticamente com base nas abas Entradas, Saidas e Custos Fixos
A4: RESUMO ACUMULADO — 2026
B5: Total Entradas | C5: Total Saidas | D5: Custos Fixos Acum. | E5: Lucro Liquido | F5: Margem Liquida
B6: =IFERROR(SUMIFS(Entradas!G:G,Entradas!A:A,">0"),0) -> 233509.26 | C6: =IFERROR(SUMIFS(Saidas!F:F,Saidas!A:A,">0"),0) -> 185491.24 | D6: =IFERROR('Custos Fixos'!B19*2,0) -> 0 | E6: =IFERROR(B6-C6-D6,0) -> 48018.02 | F6: =IFERROR(E6/B6,0) -> 0.20563647
A8: RESULTADO POR MES
B9: Mes | C9: Entradas (R$) | D9: Saidas (R$) | E9: Custos Fixos (R$) | F9: Resultado (R$) | G9: Margem (%)
B10: Abril/26 | C10: =IFERROR(SUMIFS(Entradas!G:G,Entradas!A:A,">="&DATE(2026,4,1),Entradas!A:A,"<="&EOMONTH(DATE(2026,4,1),0)),0) -> 15546.57 | D10: =IFERROR(SUMIFS(Saidas!F:F,Saidas!A:A,">="&DATE(2026,4,1),Saidas!A:A,"<="&EOMONTH(DATE(2026,4,1),0)),0) -> 4722.73 | E10: =IFERROR('Custos Fixos'!B19,0) | F10: =IFERROR(C10-D10-E10,0) -> 10823.84 | G10: =IFERROR(F10/C10,0) -> 0.69622045
B11: Maio/26 | C11: =IFERROR(SUMIFS(Entradas!G:G,Entradas!A:A,">="&DATE(2026,5,1),Entradas!A:A,"<="&EOMONTH(DATE(2026,5,1),0)),0) -> 67162.93 | D11: =IFERROR(SUMIFS(Saidas!F:F,Saidas!A:A,">="&DATE(2026,5,1),Saidas!A:A,"<="&EOMONTH(DATE(2026,5,1),0)),0) -> 46570 | E11: =IFERROR('Custos Fixos'!B19,0) | F11: =IFERROR(C11-D11-E11,0) -> 20592.93 | G11: =IFERROR(F11/C11,0) -> 0.30661155
B12: Junho/26 | C12: =IFERROR(SUMIFS(Entradas!G:G,Entradas!A:A,">="&DATE(2026,6,1),Entradas!A:A,"<="&EOMONTH(DATE(2026,6,1),0)),0) -> 55790.8 | D12: =IFERROR(SUMIFS(Saidas!F:F,Saidas!A:A,">="&DATE(2026,6,1),Saidas!A:A,"<="&EOMONTH(DATE(2026,6,1),0)),0) -> 56761.47 | E12: =IFERROR('Custos Fixos'!B19,0) | F12: =IFERROR(C12-D12-E12,0) -> -970.67 | G12: =IFERROR(F12/C12,0) -> -0.017398388
B13: Julho/26 | C13: =IFERROR(SUMIFS(Entradas!G:G,Entradas!A:A,">="&DATE(2026,7,1),Entradas!A:A,"<="&EOMONTH(DATE(2026,7,1),0)),0) -> 95008.96 | D13: =IFERROR(SUMIFS(Saidas!F:F,Saidas!A:A,">="&DATE(2026,7,1),Saidas!A:A,"<="&EOMONTH(DATE(2026,7,1),0)),0) -> 77437.04 | E13: =IFERROR('Custos Fixos'!B19,0) | F13: =IFERROR(C13-D13-E13,0) -> 17571.92 | G13: =IFERROR(F13/C13,0) -> 0.18495014
B14: Agosto/26 | C14: =IFERROR(SUMIFS(Entradas!G:G,Entradas!A:A,">="&DATE(2026,8,1),Entradas!A:A,"<="&EOMONTH(DATE(2026,8,1),0)),0) -> 0 | D14: =IFERROR(SUMIFS(Saidas!F:F,Saidas!A:A,">="&DATE(2026,8,1),Saidas!A:A,"<="&EOMONTH(DATE(2026,8,1),0)),0) -> 0 | E14: =IFERROR('Custos Fixos'!B19,0) | F14: =IFERROR(C14-D14-E14,0) -> 0 | G14: =IFERROR(F14/C14,0) -> 0
B15: Setembro/26 | C15: =IFERROR(SUMIFS(Entradas!G:G,Entradas!A:A,">="&DATE(2026,9,1),Entradas!A:A,"<="&EOMONTH(DATE(2026,9,1),0)),0) -> 0 | D15: =IFERROR(SUMIFS(Saidas!F:F,Saidas!A:A,">="&DATE(2026,9,1),Saidas!A:A,"<="&EOMONTH(DATE(2026,9,1),0)),0) -> 0 | E15: =IFERROR('Custos Fixos'!B19,0) | F15: =IFERROR(C15-D15-E15,0) -> 0 | G15: =IFERROR(F15/C15,0) -> 0
B16: Outubro/26 | C16: =IFERROR(SUMIFS(Entradas!G:G,Entradas!A:A,">="&DATE(2026,10,1),Entradas!A:A,"<="&EOMONTH(DATE(2026,10,1),0)),0) -> 0 | D16: =IFERROR(SUMIFS(Saidas!F:F,Saidas!A:A,">="&DATE(2026,10,1),Saidas!A:A,"<="&EOMONTH(DATE(2026,10,1),0)),0) -> 0 | E16: =IFERROR('Custos Fixos'!B19,0) | F16: =IFERROR(C16-D16-E16,0) -> 0 | G16: =IFERROR(F16/C16,0) -> 0
B17: Novembro/26 | C17: =IFERROR(SUMIFS(Entradas!G:G,Entradas!A:A,">="&DATE(2026,11,1),Entradas!A:A,"<="&EOMONTH(DATE(2026,11,1),0)),0) -> 0 | D17: =IFERROR(SUMIFS(Saidas!F:F,Saidas!A:A,">="&DATE(2026,11,1),Saidas!A:A,"<="&EOMONTH(DATE(2026,11,1),0)),0) -> 0 | E17: =IFERROR('Custos Fixos'!B19,0) | F17: =IFERROR(C17-D17-E17,0) -> 0 | G17: =IFERROR(F17/C17,0) -> 0
B18: Dezembro/26 | C18: =IFERROR(SUMIFS(Entradas!G:G,Entradas!A:A,">="&DATE(2026,12,1),Entradas!A:A,"<="&EOMONTH(DATE(2026,12,1),0)),0) -> 0 | D18: =IFERROR(SUMIFS(Saidas!F:F,Saidas!A:A,">="&DATE(2026,12,1),Saidas!A:A,"<="&EOMONTH(DATE(2026,12,1),0)),0) -> 0 | E18: =IFERROR('Custos Fixos'!B19,0) | F18: =IFERROR(C18-D18-E18,0) -> 0 | G18: =IFERROR(F18/C18,0) -> 0
B19: TOTAL | C19: =SUM(C10:C18) -> 233509.26 | D19: =SUM(D10:D18) -> 185491.24 | E19: =SUM(E10:E18) -> 0 | F19: =SUM(F10:F18) -> 48018.02 | G19: =SUM(G10:G18) -> 1.1703837
A21: Dica: preencha as abas Entradas, Saidas e Custos Fixos. Este painel atualiza sozinho.
A23: POSICAO DE CAIXA PREVISTA
B24: A Receber (pendente) | C24: A Pagar (pendente) | D24: Saldo Previsto
B25: =IFERROR(SUMIF('Contas a Receber'!F:F,"Pendente",'Contas a Receber'!C:C),0) -> 45653.12 | C25: =IFERROR(SUMIF('Contas a Pagar'!G5:G110,"Pendente",'Contas a Pagar'!D5:D110)+SUMIF('Contas a Pagar'!G5:G110,"Atrasado",'Contas a Pagar'!D5:D110),0) -> 35667.53 | D25: =IFERROR(B25-C25,0) -> 9985.59
A27: Saldo Previsto = valores que ainda vao entrar menos valores que ainda precisa pagar.

Sheet Entradas
A1: REGISTRO DE ENTRADAS — RECEITAS
A2: Registre toda receita recebida. Preencha sempre a Categoria para o DRE funcionar.
A3: Data | B3: Descricao | C3: Cliente | D3: Categoria | E3: Parcela | F3: Conta | G3: Valor (R$) | H3: Observacoes
A4: 46130 | B4: Comissão 3 Vendas Soraya (Vista di Mari 1303, 1213 / MLar Cambeba 705) — Pt1 | C4: Vista di Mari | D4: Comissão | E4: 1/2 | F4: Reno PF | G4: 5655.57
A5: 46135 | B5: Comissão 3 Vendas Soraya (Vista di Mari 1303, 1213 / MLar Cambeba 705) — Pt2 | C5: Vista di Mari | D5: Comissão | E5: 2/2 | F5: Reno PF | G5: 4891
A6: 46142 | B6: Aporte Reno | C6: Reno | D6: Outros | E6: — | F6: C6 — RE9 Imob | G6: 5000 | H6: Aporte sócio
A7: 46147 | B7: Comissão Venda Reno — Vibe Meireles Ap. 2103 | C7: Vibe Meireles | D7: Comissão | E7: 1/1 | F7: C6 — RE9 Imob | G7: 24006.42 | H7: Corretor: Reno
A8: 46160 | B8: Bonus Venda Reno — Bella Aldeota (Mateus J.) | C8: Bella Aldeota | D8: Comissão | E8: 46023 | F8: C6 — RE9 Imob | G8: 2990.57
A9: 46160 | B9: Comissão Venda Reno — Bella Aldeota (Mateus J.) | C9: Bella Aldeota | D9: Comissão | E9: 46054 | F9: C6 — RE9 Imob | G9: 10800.53
A10: 46160 | B10: Comissão Venda Reno - Maré - Beatriz | C10: Maré | D10: Comissão | E10: 46023 | F10: C6 — RE9 Imob | G10: 29365.41
A11: 46191 | B11: Comissão Venda Reno - MLar Kennedy - Lia e Jonathan | C11: MLar Kennedy | D11: Comissão | E11: 46023 | F11: C6 — RE9 Imob | G11: 14933.56
A12: 46196 | B12: Comissão Venda Reno - MLar - Rafael Herminio | C12: Mlar Jacarey | D12: Comissão | E12: 46024 | F12: C6 — RE9 Imob | G12: 13505.8
A13: 46204 | B13: Bonus Venda Reno - MLar Kennedy - Lia e Jonathan | C13: MLar Kennedy | D13: Comissão | E13: 46023 | F13: C6 — RE9 Imob | G13: 2894.1
A14: 46174 | B14: Comissão Venda Reno - Gilson - Beatriz | C14: Maré | D14: Comissão | E14: 46023 | F14: C6 — RE9 Imob | G14: 27351.44
A15: 46216 | B15: Comissão Venda Reno — Bella Aldeota | C15: Bella Aldeota | D15: Comissão | E15: 46023 | F15: C6 — RE9 Imob | G15: 19526.19
A16: 46216 | B16: Comissão Venda Reno — Bella Aldeota (Mateus J.) | C16: Bella Aldeota | D16: Comissão | E16: 46055 | F16: C6 — RE9 Imob | G16: 10800.53
A17: 46216 | B17: Comissão Venda Reno — Maré (Mara) | C17: Maré | D17: Comissão | E17: 46055 | F17: C6 — RE9 Imob | G17: 25038.04
A18: 46223 | B18: Comissão Venda Reno — Bella Aldeota (Jaime) | C18: Bella Aldeota | D18: Comissão | E18: 46056 | F18: C6 — RE9 Imob | G18: 17485.5
A19: 46223 | B19: Investimento Tráfego - PraMorar | C19: Bella Aldeota | D19: Comissão | E19: 46056 | F19: C6 — RE9 Imob | G19: 1900
... A22: 46230 | B22: Bonus - Gilson | C22: Bella Aldeota | D22: Bônus | E22: 46025 | F22: C6 — RE9 Imob | G22: 9647
A23: TOTAL | G23: =SUM(G4:G22) -> 233509.26
A25: Para adicionar: insira uma linha ANTES do TOTAL. Categorias: Comissão | Tráfego Pago | Aporte | Outros

Sheet Saidas
A1: REGISTRO DE SAIDAS — DESPESAS
A2: Registre toda despesa variavel. Categorias: Marketing | Alimentação | Transporte | Software | Equipamento | Outros
A3: Data | B3: Descricao | C3: Pago a / Fornecedor | D3: Categoria | E3: Forma Pgto | F3: Valor (R$) | G3: Comprovante | H3: Observacoes | I3: Pago?
A4: 46134 | B4: Compra 06 cabecas de carregadores | C4: Amazon | D4: Equipamento | E4: Cartão | F4: 143.58 | G4: Pago - Comprovante - compra de 06 cabeças de carregadores.jpeg | I4: Sim
A5: 46135 | B5: Saldo Meta — Bella Aldeota e Bella Rio | C5: Meta | D5: Marketing | E5: Pix | F5: 1000 | G5: Pago - Saldo Campanha - Bella Aldeota e Bella Rio.jpeg | I5: Sim
A6: 46135 | B6: Saldo Meta — BSWave e Maré | C6: Meta | D6: Marketing | E6: Pix | F6: 750 | G6: Pago - Saldo Campanha - BS Wave e Mare.jpeg | I6: Sim
A7: 46135 | B7: Saldo Meta — MLar Cambeba e Lago | C7: Meta | D7: Marketing | E7: Pix | F7: 750 | G7: Pago - Saldo Campanha - MLar Cambeba e Lago.jpeg | I7: Sim
A8: 46135 | B8: Saldo Google — GAds Internacional | C8: Google | D8: Marketing | E8: Pix | F8: 400 | G8: Pago - Saldo Campanha - GAds Internacional.jpeg | I8: Sim
A9: 46135 | B9: Compra 08 cabos carregadores + Régua | C9: Amazon | D9: Equipamento | E9: Cartão | F9: 138.03 | I9: Sim
A10: 46136 | B10: Compra 10 suportes de celulares | C10: Mercado Livre | D10: Equipamento | E10: Cartão | F10: 41.12 | G10: 10 suportes de celulares.jpeg | I10: Sim
A11: 46139 | B11: Saldo Google — GAds Fortaleza RE9 Imob | C11: Google | D11: Marketing | E11: Pix | F11: 1000 | G11: Pago - Saldo Campanha - GAds Fortaleza.png | I11: Sim
A12: 46139 | B12: Saldo Meta — MLar Cambeba e Lago | C12: Meta | D12: Marketing | E12: Pix | F12: 500 | G12: Pago - Saldo Campanha - Meta MLar Cambeba e Lago.png | I12: Sim
A13: 46144 | B13: Saldo Meta — Atlântico, Orizon e Seano | C13: Meta | D13: Marketing | E13: Cartão | F13: 500 | G13: Pago - Saldo Meta - AtlanticoSeanoOrizon - Maio26.pdf | I13: Sim
A14: 46144 | B14: Saldo Meta — Bella Aldeota e Bella Rio | C14: Meta | D14: Marketing | E14: Cartão | F14: 1000 | G14: Pago - Saldo Meta - Bella Aldeota e Bella Rio - Maio26.pdf | I14: Sim
A15: 46144 | B15: Saldo Meta — BSWave e Maré | C15: Meta | D15: Marketing | E15: Cartão | F15: 400 | G15: Pago - Saldo Meta - BSWave e Mare - Maio26.pdf | I15: Sim
A16: 46144 | B16: Saldo Meta — MLar Cambeba e Lago | C16: Meta | D16: Marketing | E16: Cartão | F16: 400 | G16: Pago - Saldo Meta - MLar Cambeba e Lago - Maio26.pdf | I16: Sim
A17: 46147 | B17: Pagamento Comissão Corretor Reno — Vibe 2103 | C17: Reno | D17: Comissão | E17: Pix | F17: 12003.21 | G17: Pago - Comissão Reno - Vibe Meireles Ap2103.jpeg | I17: Sim
A18: 46147 | B18: Pagamento Angélica — Vibe Meireles 2103 | C18: Angélica | D18: Comissão | E18: Pix | F18: 500 | G18: Pago - Comissao1 Angelica Mai26.pdf | I18: Sim
A19: 46147 | B19: 50% Placas Porta RE9 — CEPlacas | C19: CE Placas | D19: Equipamento | E19: Pix | F19: 375 | G19: Pago - Placas RE9 pt1.pdf | I19: Sim
A20: 46149 | B20: Saldo Meta — Atlântico, Orizon e Seano | C20: Meta | D20: Marketing | E20: Pix | F20: 2652.04 | G20: Pago - Saldo Meta - AtlanticoSeanoOrizon 2 - Maio26.jpeg | I20: Sim
A21: 46149 | B21: Saldo Meta — Bella Aldeota e Bella Rio | C21: Meta | D21: Marketing | E21: Pix | F21: 2000 | G21: Pago - Saldo Meta - BellaAldeota e Bella Rio 2 - Maio26.jpeg | I21: Sim
... A109: 46223 | B109: Saldo Google - Re9 Imob Outros Estados | C109: Google | D109: Marketing | E109: Pix | F109: 400 | G109: Pago - Saldo Google - Re9 Imob Outros Estados.jpeg | I109: Sim
A110: 46231 | B110: Pagamento OLX | C110: Reno | D110: Marketing | E110: Pix | F110: 275.9 | G110: Pago - OLX.jpeg
A111: 46232 | B111: Saldo Google 500 - RE9 Imob - Outros Estados | C111: Google | D111: Marketing | E111: Pix | F111: 500 | G111: Pago - Saldo Google 500 - RE9 Imob - Outros Estados.jpeg
A112: 46232 | B112: Saldo Meta 2000 - Bella Aldeota, Rio, Oasy e Myrage | C112: Meta | D112: Marketing | E112: Pix | F112: 2000 | G112: Pago - Saldo Meta 2000 - Bella Aldeota, Rio, Oasy e Myrage.jpeg
A113: 46232 | B113: Saldo Meta 1000 - MLar Cambeba, Lago e Inc Cambeba | C113: Meta | D113: Marketing | E113: Pix | F113: 1000 | G113: Pago - Saldo Meta 1000 - MLar Cambeba, Lago e Inc Cambeba.jpeg
A114: 46232 | B114: Saldo Meta 2000 - Maré, BS Wave e Vista Coqueiral | C114: Meta | D114: Marketing | E114: Pix | F114: 2000 | G114: Pago - Saldo Meta 2000 - Maré, BS Wave e Vista Coqueiral.jpeg
A115: 46232 | B115: Saldo Meta 1000 - La Vie e Inc Parquelândia | C115: Meta | D115: Marketing | E115: Pix | F115: 1000 | G115: Pago - Saldo Meta 1000 - La Vie e Inc Parquelândia.jpeg
A116: 46232 | B116: Saldo Google 2000 - RE9 Imob - Fortaleza | C116: Google | D116: Marketing | E116: Pix | F116: 2000 | G116: Pago - Saldo Google 2000 - RE9 Imob - Fortaleza.jpegg
A117: 46232 | B117: Saldo Google 1000 - RE9 Imob - Imóveis Praia | C117: Google | D117: Marketing | E117: Pix | F117: 1000 | G117: Pago - Saldo Google 1000 - RE9 Imob - Imóveis Praia.jpeg
A118: TOTAL | F118: =SUM(F4:F117) -> 185491.24
A120: Categorias: Marketing | Comissão | Equipamento | Formação | Outros. Use sempre a mesma grafia.

Sheet Comissoes
A1: COMISSOES A RECEBER — CONTROLE COMPLETO
A2: Col G: imposto retido por cada construtora | Col O: Simples (3,53% fixo) | Col P: 10,49% − G | Col Q: Valor Bruto × P
A3: Corretor | B3: Cliente | C3: Empreendimento | D3: Valor Imóvel | E3: Comissão (%) | F3: Valor Bruto | G3: Imposto (Aliq) | H3: Valor Líquido | I3: Valor Corretor | J3: Valor RE9 | K3: Data Recebimento | L3: Recebido? | M3: Corretor Pago? | N3: Repasse RE9? | O3: Imposto a Pagar (%) | P3: Imposto a Pagar (R$)
A4: Soraya | B4: Nonato Gabriel Figueira | C4: Tenda — Vista di Mari (1303) | D4: 297303.06 | E4: 0.03 | F4: 8919.09 | G4: 0.000459 | H4: 8915 | I4: 5923.32 | J4: 2961.23 | K4: 46130 | L4: Sim | M4: Sim | N4: Não | O4: =MAX(0,0.08-G4) -> 0.079541 | P4: =F4*O4 -> 709.43334
A5: Soraya | B5: Clemilton Lima de Souza | C5: Tenda — Vista di Mari (1213) | D5: 297303.06 | E5: 0.04 | F5: 11892.12 | G5: 0.17737 | H5: 9782.82 | I5: 6521.86 | J5: 3260.96 | K5: 46135 | L5: Sim | M5: Sim | N5: Não | O5: =MAX(0,0.08-G5) -> 0 | P5: =F5*O5 -> 0
A6: André | B6: Lucirene Souza | C6: MLar Kennedy — Bônus R$5.000 | D6: 5000 | E6: 1 | F6: 5000 | G6: 0.1049 | H6: 4475.5 | I6: 2237.75 | J6: 2237.75 | K6: 46203 | L6: Não | M6: Não | N6: Não | O6: =MAX(0,0.08-G6) -> 0 | P6: =F6*O6 -> 0
A7: André | B7: Lucirene Souza | C7: MLar Kennedy — Apto 1106 Torre Due | D7: 371399.84 | E7: 0.04 | F7: 14855.99 | G7: 0.1049 | H7: 13297.6 | I7: 6648.8 | J7: 6648.8 | K7: 46051 | L7: Sim | M7: Sim | N7: Não | O7: =MAX(0,0.08-G7) -> 0 | P7: =F7*O7 -> 0
A8: André | B8: Luana | C8: MLar Cambeba — Apto. 1104 Torre Due | D8: 349804.35 | E8: 0.04 | F8: 13992.17 | G8: 0.1049 | H8: 12524.39 | I8: 6262.2 | J8: 6262.2 | K8: 46203 | L8: Não | M8: Não | N8: Não | O8: =MAX(0,0.08-G8) -> 0 | P8: =F8*O8 -> 0
A9: André | B9: Vinicius | C9: MLar Cambeba — Apto. 905 Torre Due | D9: 347410.55 | E9: 0.04 | F9: 13896.42 | G9: 0.1049 | H9: 12438.69 | I9: 6219.34 | J9: 6219.34 | K9: 46203 | L9: Não | M9: Não | N9: Não | O9: =MAX(0,0.08-G9) -> 0 | P9: =F9*O9 -> 0
A10: Lucas | B10: Juliana Pontes | C10: MLar Cambeba — Apto. 705 | D10: 352531.5 | E10: 0.04 | F10: 14101.26 | G10: 0.08 | H10: 12973.16 | I10: R$ 6.486,58 | J10: 4324.38 | K10: 46235 | L10: Sim | M10: Sim | N10: Não | O10: =MAX(0,0.08-G10) -> 0 | P10: =F10*O10 -> 0
A11: Reno | B11: Rafael Hermínio | C11: MLar Jacarey — 808 Torre Blues | D11: 350000 | E11: 0.04 | F11: 14000 | G11: 0.0353 | H11: =F11-(F11*G11) -> 13505.8 | I11: 6752.9 | J11: 6752.9 | K11: 46203 | L11: Sim | M11: Sim | N11: Não | O11: =MAX(0,0.08-G11) -> 0.0447 | P11: =F11*O11 -> 625.8
A12: Reno | B12: Rafael Ditolvo | C12: Bella Aldeota — 601 Torre 2 | D12: 506017.33 | E12: 0.04 | F12: 20240.69 | G12: 0.0353 | H12: 19526.19 | I12: 9763.095 | J12: 9763.095 | K12: 46210 | L12: Sim | M12: Sim | N12: Não | O12: =MAX(0,0.08-G12) -> 0.0447 | P12: =F12*O12 -> 904.75884
A13: Reno | B13: Marcio Anderson | C13: Bella Aldeota — 1306 Torre 1 | D13: 474002.21 | E13: 0.04 | F13: 18960.09 | G13: 0.1049 | H13: 16971.18 | I13: 8485.5876 | J13: 16971.18 | K13: 46234 | L13: Não | M13: Não | N13: Não | O13: =MAX(0,0.08-G13) -> 0 | P13: =F13*O13 -> 0
A14: Reno | B14: Beatriz Dias | C14: Maré (Marquise) | D14: 760998.58 | E14: 0.04 | F14: 30439.94 | G14: 0.1049 | H14: 27246.79 | I14: 13623.4 | J14: 13623.4 | K14: 46157 | L14: Sim | M14: Sim | N14: Sim | O14: =MAX(0,0.08-G14) -> 0 | P14: =F14*O14 -> 0
A15: Reno | B15: Sávio Santanta | C15: Vibe Meireles - Apto 2103 | D15: 622121.6 | E15: 0.04 | F15: 24884.86 | G15: 0.1049 | H15: 22274.44 | I15: 11137.22 | J15: 11137.22 | K15: 46147 | L15: Sim | M15: Sim | N15: Não | O15: =MAX(0,0.08-G15) -> 0 | P15: =F15*O15 -> 0
A16: Reno | B16: Mateus Jereissati | C16: Bella Aldeota - parcela 01 | D16: 559786.91 | E16: 0.04 | F16: 22391.48 | G16: 0.0353 | H16: 21601.06 | I16: 10800.53 | J16: 10800.53 | K16: 46173 | L16: Sim | M16: Sim | N16: Não | O16: =MAX(0,0.08-G16) -> 0.0447 | P16: =F16*O16 -> 1000.8992
A17: Reno | B17: Mateus Jereissati | C17: Bella Aldeota - parcela 02 | D17: 559786.91 | E17: 0.04 | F17: 22391.48 | G17: 0.0353 | H17: 21601.06 | I17: 10800.53 | J17: 10800.53 | K17: 46217 | L17: Sim | M17: Sim | N17: Não | O17: =MAX(0,0.08-G17) -> 0.0447 | P17: =F17*O17 -> 1000.8992
A18: Reno | B18: Mateus Jereissati | C18: Bella Aldeota — Bônus | D18: 3000 | E18: 0.04 | F18: 3000 | G18: 0.0353 | H18: 2990.57 | I18: 1495 | J18: 1495 | K18: 46173 | L18: Sim | M18: Sim | N18: Sim | O18: =MAX(0,0.08-G18) -> 0.0447 | P18: =F18*O18 -> 134.1
A19: Reno | B19: Lia de Sousa Alexandre e Jonathan Silva Santos | C19: MLar Kennedy | D19: 387000 | E19: 0.04 | F19: =D19*E19 -> 15480 | G19: 0.0353 | H19: =F19-(G19*F19) -> 14933.556 | I19: =H19/2 -> 7466.778 | J19: =H19-I19 -> 7466.778 | K19: 46192 | L19: Sim | M19: Sim | N19: Sim | O19: =MAX(0,0.08-G19) -> 0.0447 | P19: =F19*O19 -> 691.956
A20: Reno | B20: Gilson Ferreira de Andrade | C20: Maré (Marquise) | D20: 708807 | E20: 0.04 | F20: =D20*E20 -> 28352.28 | G20: 0.0353 | H20: =F20-(G20*F20) -> 27351.445 | I20: =H20/2 -> 13675.722 | J20: =H20-I20 -> 13675.722 | K20: 46203 | L20: Sim | M20: Sim | N20: Não | O20: =MAX(0,0.08-G20) -> 0.0447 | P20: =F20*O20 -> 1267.3469
A21: Reno | B21: José Jaime do Nascimento | C21: Bella Aldeota - Apto: 603 (Torre 1) | D21: 453132.94 | E21: 0.04 | F21: =D21*E21 -> 18125.318 | G21: 0.0353 | H21: =F21-(G21*F21) -> 17485.494 | I21: =H21/2 -> 8742.7469 | J21: =H21-I21 -> 8742.7469 | K21: 46217 | L21: Sim | M21: Sim | N21: Não | O21: =MAX(0,0.08-G21) -> 0.0447 | P21: =F21*O21 -> 810.2017
A22: Soraya | B22: Mara Tailane Moreira da Silva | C22: Enjoy - Apto 1201 | D22: 594104.25 | E22: 0.04 | F22: =D22*E22 -> 23764.17 | G22: 0.0353 | H22: =F22-(G22*F22) -> 22925.295 | I22: =H22/2 -> 11462.647 | J22: =H22-I22 -> 11462.647 | K22: 46260 | L22: Não | M22: Não | N22: Não
A23: TOTAIS | D23: =SUM(D4:D18) -> 5856465.9 | F23: =SUM(F4:F18) -> 238965.59 | H23: =SUM(H4:H18) -> 220124.25 | I23: =SUM(I4:I18) -> 106671.53 | J23: =SUM(J4:J18) -> 113258.51 | P23: =SUM(P4:P18) -> 4375.8905
B25: RESUMO: Valores pendentes de recebimento pela RE9
B26: RE9 — Total a Receber (pendente) | C26: =SUMIF(L4:L18,"Não",J4:J18) -> 31690.47
B27: RE9 — Total já Recebido | C27: =SUMIF(L4:L18,"Sim",J4:J18) -> 81568.045
B28: RE9 — Total Geral | C28: =SUM(J4:J18) -> 113258.51

Sheet DRE
A1: DRE — DEMONSTRATIVO DE RESULTADO — 2026
A2: Calculado automaticamente. Aliquotas configuradas na aba Custos Fixos (celulas B22 e B23).
A4: LINHA | B4: Abr/26 | C4: Mai/26 | D4: Jun/26 | E4: Jul/26 | F4: Ago/26 | G4: Set/26 | H4: Out/26 | I4: Nov/26 | J4: Dez/26 | K4: TOTAL ANO
A5: (+) RECEITA BRUTA | B5: =IFERROR(SUMIFS(Entradas!G:G,Entradas!A:A,">="&DATE(2026,4,1),Entradas!A:A,"<="&EOMONTH(DATE(2026,4,1),0)),0) -> 15546.57 | C5: =IFERROR(SUMIFS(Entradas!G:G,Entradas!A:A,">="&DATE(2026,5,1),Entradas!A:A,"<="&EOMONTH(DATE(2026,5,1),0)),0) -> 67162.93 | D5: =IFERROR(SUMIFS(Entradas!G:G,Entradas!A:A,">="&DATE(2026,6,1),Entradas!A:A,"<="&EOMONTH(DATE(2026,6,1),0)),0) -> 55790.8 | E5: =IFERROR(SUMIFS(Entradas!G:G,Entradas!A:A,">="&DATE(2026,7,1),Entradas!A:A,"<="&EOMONTH(DATE(2026,7,1),0)),0) -> 95008.96 | F5: =IFERROR(SUMIFS(Entradas!G:G,Entradas!A:A,">="&DATE(2026,8,1),Entradas!A:A,"<="&EOMONTH(DATE(2026,8,1),0)),0) -> 0 | G5: =IFERROR(SUMIFS(Entradas!G:G,Entradas!A:A,">="&DATE(2026,9,1),Entradas!A:A,"<="&EOMONTH(DATE(2026,9,1),0)),0) -> 0 | H5: =IFERROR(SUMIFS(Entradas!G:G,Entradas!A:A,">="&DATE(2026,10,1),Entradas!A:A,"<="&EOMONTH(DATE(2026,10,1),0)),0) -> 0 | I5: =IFERROR(SUMIFS(Entradas!G:G,Entradas!A:A,">="&DATE(2026,11,1),Entradas!A:A,"<="&EOMONTH(DATE(2026,11,1),0)),0) -> 0 | J5: =IFERROR(SUMIFS(Entradas!G:G,Entradas!A:A,">="&DATE(2026,12,1),Entradas!A:A,"<="&EOMONTH(DATE(2026,12,1),0)),0) -> 0 | K5: =SUM(B5:J5) -> 233509.26
A6: Comissoes | B6: =IFERROR(SUMIFS(Entradas!G:G,Entradas!A:A,">="&DATE(2026,4,1),Entradas!A:A,"<="&EOMONTH(DATE(2026,4,1),0),Entradas!E:E,"Comissão"),0) -> 0 | C6: =IFERROR(SUMIFS(Entradas!G:G,Entradas!A:A,">="&DATE(2026,5,1),Entradas!A:A,"<="&EOMONTH(DATE(2026,5,1),0),Entradas!E:E,"Comissão"),0) -> 0 | D6: =IFERROR(SUMIFS(Entradas!G:G,Entradas!A:A,">="&DATE(2026,6,1),Entradas!A:A,"<="&EOMONTH(DATE(2026,6,1),0),Entradas!E:E,"Comissão"),0) -> 0 | E6: =IFERROR(SUMIFS(Entradas!G:G,Entradas!A:A,">="&DATE(2026,7,1),Entradas!A:A,"<="&EOMONTH(DATE(2026,7,1),0),Entradas!E:E,"Comissão"),0) -> 0 | F6: =IFERROR(SUMIFS(Entradas!G:G,Entradas!A:A,">="&DATE(2026,8,1),Entradas!A:A,"<="&EOMONTH(DATE(2026,8,1),0),Entradas!E:E,"Comissão"),0) -> 0 | G6: =IFERROR(SUMIFS(Entradas!G:G,Entradas!A:A,">="&DATE(2026,9,1),Entradas!A:A,"<="&EOMONTH(DATE(2026,9,1),0),Entradas!E:E,"Comissão"),0) -> 0 | H6: =IFERROR(SUMIFS(Entradas!G:G,Entradas!A:A,">="&DATE(2026,10,1),Entradas!A:A,"<="&EOMONTH(DATE(2026,10,1),0),Entradas!E:E,"Comissão"),0) -> 0 | I6: =IFERROR(SUMIFS(Entradas!G:G,Entradas!A:A,">="&DATE(2026,11,1),Entradas!A:A,"<="&EOMONTH(DATE(2026,11,1),0),Entradas!E:E,"Comissão"),0) -> 0 | J6: =IFERROR(SUMIFS(Entradas!G:G,Entradas!A:A,">="&DATE(2026,12,1),Entradas!A:A,"<="&EOMONTH(DATE(2026,12,1),0),Entradas!E:E,"Comissão"),0) -> 0 | K6: =SUM(B6:J6) -> 0
A7: Reembolso Trafego Pago | B7: =IFERROR(SUMIFS(Entradas!G:G,Entradas!A:A,">="&DATE(2026,4,1),Entradas!A:A,"<="&EOMONTH(DATE(2026,4,1),0),Entradas!E:E,"Tráfego Pago"),0) -> 0 | C7: =IFERROR(SUMIFS(Entradas!G:G,Entradas!A:A,">="&DATE(2026,5,1),Entradas!A:A,"<="&EOMONTH(DATE(2026,5,1),0),Entradas!E:E,"Tráfego Pago"),0) -> 0 | D7: =IFERROR(SUMIFS(Entradas!G:G,Entradas!A:A,">="&DATE(2026,6,1),Entradas!A:A,"<="&EOMONTH(DATE(2026,6,1),0),Entradas!E:E,"Tráfego Pago"),0) -> 0 | E7: =IFERROR(SUMIFS(Entradas!G:G,Entradas!A:A,">="&DATE(2026,7,1),Entradas!A:A,"<="&EOMONTH(DATE(2026,7,1),0),Entradas!E:E,"Tráfego Pago"),0) -> 0 | F7: =IFERROR(SUMIFS(Entradas!G:G,Entradas!A:A,">="&DATE(2026,8,1),Entradas!A:A,"<="&EOMONTH(DATE(2026,8,1),0),Entradas!E:E,"Tráfego Pago"),0) -> 0 | G7: =IFERROR(SUMIFS(Entradas!G:G,Entradas!A:A,">="&DATE(2026,9,1),Entradas!A:A,"<="&EOMONTH(DATE(2026,9,1),0),Entradas!E:E,"Tráfego Pago"),0) -> 0 | H7: =IFERROR(SUMIFS(Entradas!G:G,Entradas!A:A,">="&DATE(2026,10,1),Entradas!A:A,"<="&EOMONTH(DATE(2026,10,1),0),Entradas!E:E,"Tráfego Pago"),0) -> 0 | I7: =IFERROR(SUMIFS(Entradas!G:G,Entradas!A:A,">="&DATE(2026,11,1),Entradas!A:A,"<="&EOMONTH(DATE(2026,11,1),0),Entradas!E:E,"Tráfego Pago"),0) -> 0 | J7: =IFERROR(SUMIFS(Entradas!G:G,Entradas!A:A,">="&DATE(2026,12,1),Entradas!A:A,"<="&EOMONTH(DATE(2026,12,1),0),Entradas!E:E,"Tráfego Pago"),0) -> 0 | K7: =SUM(B7:J7) -> 0
A8: Outros | B8: =IFERROR(SUMIFS(Entradas!G:G,Entradas!A:A,">="&DATE(2026,4,1),Entradas!A:A,"<="&EOMONTH(DATE(2026,4,1),0),Entradas!E:E,"Outros"),0) -> 0 | C8: =IFERROR(SUMIFS(Entradas!G:G,Entradas!A:A,">="&DATE(2026,5,1),Entradas!A:A,"<="&EOMONTH(DATE(2026,5,1),0),Entradas!E:E,"Outros"),0) -> 0 | D8: =IFERROR(SUMIFS(Entradas!G:G,Entradas!A:A,">="&DATE(2026,6,1),Entradas!A:A,"<="&EOMONTH(DATE(2026,6,1),0),Entradas!E:E,"Outros"),0) -> 0 | E8: =IFERROR(SUMIFS(Entradas!G:G,Entradas!A:A,">="&DATE(2026,7,1),Entradas!A:A,"<="&EOMONTH(DATE(2026,7,1),0),Entradas!E:E,"Outros"),0) -> 0 | F8: =IFERROR(SUMIFS(Entradas!G:G,Entradas!A:A,">="&DATE(2026,8,1),Entradas!A:A,"<="&EOMONTH(DATE(2026,8,1),0),Entradas!E:E,"Outros"),0) -> 0 | G8: =IFERROR(SUMIFS(Entradas!G:G,Entradas!A:A,">="&DATE(2026,9,1),Entradas!A:A,"<="&EOMONTH(DATE(2026,9,1),0),Entradas!E:E,"Outros"),0) -> 0 | H8: =IFERROR(SUMIFS(Entradas!G:G,Entradas!A:A,">="&DATE(2026,10,1),Entradas!A:A,"<="&EOMONTH(DATE(2026,10,1),0),Entradas!E:E,"Outros"),0) -> 0 | I8: =IFERROR(SUMIFS(Entradas!G:G,Entradas!A:A,">="&DATE(2026,11,1),Entradas!A:A,"<="&EOMONTH(DATE(2026,11,1),0),Entradas!E:E,"Outros"),0) -> 0 | J8: =IFERROR(SUMIFS(Entradas!G:G,Entradas!A:A,">="&DATE(2026,12,1),Entradas!A:A,"<="&EOMONTH(DATE(2026,12,1),0),Entradas!E:E,"Outros"),0) -> 0 | K8: =SUM(B8:J8) -> 0
A9: (-) DEDUCOES / IMPOSTOS (% da receita) | B9: =IFERROR(B5*'Custos Fixos'!B21,0) -> 0 | C9: =IFERROR(C5*'Custos Fixos'!B21,0) -> 0 | D9: =IFERROR(D5*'Custos Fixos'!B21,0) -> 0 | E9: =IFERROR(E5*'Custos Fixos'!B21,0) -> 0 | F9: =IFERROR(F5*'Custos Fixos'!B21,0) -> 0 | G9: =IFERROR(G5*'Custos Fixos'!B21,0) -> 0 | H9: =IFERROR(H5*'Custos Fixos'!B21,0) -> 0 | I9: =IFERROR(I5*'Custos Fixos'!B21,0) -> 0 | J9: =IFERROR(J5*'Custos Fixos'!B21,0) -> 0 | K9: =SUM(B9:J9) -> 0
A10: (=) RECEITA LIQUIDA | B10: =IFERROR(B5-B9,0) -> 15546.57 | C10: =IFERROR(C5-C9,0) -> 67162.93 | D10: =IFERROR(D5-D9,0) -> 55790.8 | E10: =IFERROR(E5-E9,0) -> 95008.96 | F10: =IFERROR(F5-F9,0) -> 0 | G10: =IFERROR(G5-G9,0) -> 0 | H10: =IFERROR(H5-H9,0) -> 0 | I10: =IFERROR(I5-I9,0) -> 0 | J10: =IFERROR(J5-J9,0) -> 0 | K10: =SUM(B10:J10) -> 233509.26
A11: (-) DESPESAS VARIAVEIS | B11: =IFERROR(SUMIFS(Saidas!F:F,Saidas!A:A,">="&DATE(2026,4,1),Saidas!A:A,"<="&EOMONTH(DATE(2026,4,1),0)),0) -> 4722.73 | C11: =IFERROR(SUMIFS(Saidas!F:F,Saidas!A:A,">="&DATE(2026,5,1),Saidas!A:A,"<="&EOMONTH(DATE(2026,5,1),0)),0) -> 46570 | D11: =IFERROR(SUMIFS(Saidas!F:F,Saidas!A:A,">="&DATE(2026,6,1),Saidas!A:A,"<="&EOMONTH(DATE(2026,6,1),0)),0) -> 56761.47 | E11: =IFERROR(SUMIFS(Saidas!F:F,Saidas!A:A,">="&DATE(2026,7,1),Saidas!A:A,"<="&EOMONTH(DATE(2026,7,1),0)),0) -> 77437.04 | F11: =IFERROR(SUMIFS(Saidas!F:F,Saidas!A:A,">="&DATE(2026,8,1),Saidas!A:A,"<="&EOMONTH(DATE(2026,8,1),0)),0) -> 0 | G11: =IFERROR(SUMIFS(Saidas!F:F,Saidas!A:A,">="&DATE(2026,9,1),Saidas!A:A,"<="&EOMONTH(DATE(2026,9,1),0)),0) -> 0 | H11: =IFERROR(SUMIFS(Saidas!F:F,Saidas!A:A,">="&DATE(2026,10,1),Saidas!A:A,"<="&EOMONTH(DATE(2026,10,1),0)),0) -> 0 | I11: =IFERROR(SUMIFS(Saidas!F:F,Saidas!A:A,">="&DATE(2026,11,1),Saidas!A:A,"<="&EOMONTH(DATE(2026,11,1),0)),0) -> 0 | J11: =IFERROR(SUMIFS(Saidas!F:F,Saidas!A:A,">="&DATE(2026,12,1),Saidas!A:A,"<="&EOMONTH(DATE(2026,12,1),0)),0) -> 0 | K11: =SUM(B11:J11) -> 185491.24
A12: Marketing / Trafego | B12: =IFERROR(SUMIFS(Saidas!F:F,Saidas!A:A,">="&DATE(2026,4,1),Saidas!A:A,"<="&EOMONTH(DATE(2026,4,1),0),Saidas!D:D,"Marketing"),0) -> 4400 | C12: =IFERROR(SUMIFS(Saidas!F:F,Saidas!A:A,">="&DATE(2026,5,1),Saidas!A:A,"<="&EOMONTH(DATE(2026,5,1),0),Saidas!D:D,"Marketing"),0) -> 21936.04 | D12: =IFERROR(SUMIFS(Saidas!F:F,Saidas!A:A,">="&DATE(2026,6,1),Saidas!A:A,"<="&EOMONTH(DATE(2026,6,1),0),Saidas!D:D,"Marketing"),0) -> 19229 | E12: =IFERROR(SUMIFS(Saidas!F:F,Saidas!A:A,">="&DATE(2026,7,1),Saidas!A:A,"<="&EOMONTH(DATE(2026,7,1),0),Saidas!D:D,"Marketing"),0) -> 33951.62 | F12: =IFERROR(SUMIFS(Saidas!F:F,Saidas!A:A,">="&DATE(2026,8,1),Saidas!A:A,"<="&EOMONTH(DATE(2026,8,1),0),Saidas!D:D,"Marketing"),0) -> 0 | G12: =IFERROR(SUMIFS(Saidas!F:F,Saidas!A:A,">="&DATE(2026,9,1),Saidas!A:A,"<="&EOMONTH(DATE(2026,9,1),0),Saidas!D:D,"Marketing"),0) -> 0 | H12: =IFERROR(SUMIFS(Saidas!F:F,Saidas!A:A,">="&DATE(2026,10,1),Saidas!A:A,"<="&EOMONTH(DATE(2026,10,1),0),Saidas!D:D,"Marketing"),0) -> 0 | I12: =IFERROR(SUMIFS(Saidas!F:F,Saidas!A:A,">="&DATE(2026,11,1),Saidas!A:A,"<="&EOMONTH(DATE(2026,11,1),0),Saidas!D:D,"Marketing"),0) -> 0 | J12: =IFERROR(SUMIFS(Saidas!F:F,Saidas!A:A,">="&DATE(2026,12,1),Saidas!A:A,"<="&EOMONTH(DATE(2026,12,1),0),Saidas!D:D,"Marketing"),0) -> 0 | K12: =SUM(B12:J12) -> 79516.66
A13: Alimentacao / Refeicoes | B13: =IFERROR(SUMIFS(Saidas!F:F,Saidas!A:A,">="&DATE(2026,4,1),Saidas!A:A,"<="&EOMONTH(DATE(2026,4,1),0),Saidas!D:D,"Alimentação"),0) -> 0 | C13: =IFERROR(SUMIFS(Saidas!F:F,Saidas!A:A,">="&DATE(2026,5,1),Saidas!A:A,"<="&EOMONTH(DATE(2026,5,1),0),Saidas!D:D,"Alimentação"),0) -> 0 | D13: =IFERROR(SUMIFS(Saidas!F:F,Saidas!A:A,">="&DATE(2026,6,1),Saidas!A:A,"<="&EOMONTH(DATE(2026,6,1),0),Saidas!D:D,"Alimentação"),0) -> 0 | E13: =IFERROR(SUMIFS(Saidas!F:F,Saidas!A:A,">="&DATE(2026,7,1),Saidas!A:A,"<="&EOMONTH(DATE(2026,7,1),0),Saidas!D:D,"Alimentação"),0) -> 0 | F13: =IFERROR(SUMIFS(Saidas!F:F,Saidas!A:A,">="&DATE(2026,8,1),Saidas!A:A,"<="&EOMONTH(DATE(2026,8,1),0),Saidas!D:D,"Alimentação"),0) -> 0 | G13: =IFERROR(SUMIFS(Saidas!F:F,Saidas!A:A,">="&DATE(2026,9,1),Saidas!A:A,"<="&EOMONTH(DATE(2026,9,1),0),Saidas!D:D,"Alimentação"),0) -> 0 | H13: =IFERROR(SUMIFS(Saidas!F:F,Saidas!A:A,">="&DATE(2026,10,1),Saidas!A:A,"<="&EOMONTH(DATE(2026,10,1),0),Saidas!D:D,"Alimentação"),0) -> 0 | I13: =IFERROR(SUMIFS(Saidas!F:F,Saidas!A:A,">="&DATE(2026,11,1),Saidas!A:A,"<="&EOMONTH(DATE(2026,11,1),0),Saidas!D:D,"Alimentação"),0) -> 0 | J13: =IFERROR(SUMIFS(Saidas!F:F,Saidas!A:A,">="&DATE(2026,12,1),Saidas!A:A,"<="&EOMONTH(DATE(2026,12,1),0),Saidas!D:D,"Alimentação"),0) -> 0 | K13: =SUM(B13:J13) -> 0
A14: Transporte / Combustivel | B14: =IFERROR(SUMIFS(Saidas!F:F,Saidas!A:A,">="&DATE(2026,4,1),Saidas!A:A,"<="&EOMONTH(DATE(2026,4,1),0),Saidas!D:D,"Transporte"),0) -> 0 | C14: =IFERROR(SUMIFS(Saidas!F:F,Saidas!A:A,">="&DATE(2026,5,1),Saidas!A:A,"<="&EOMONTH(DATE(2026,5,1),0),Saidas!D:D,"Transporte"),0) -> 0 | D14: =IFERROR(SUMIFS(Saidas!F:F,Saidas!A:A,">="&DATE(2026,6,1),Saidas!A:A,"<="&EOMONTH(DATE(2026,6,1),0),Saidas!D:D,"Transporte"),0) -> 0 | E14: =IFERROR(SUMIFS(Saidas!F:F,Saidas!A:A,">="&DATE(2026,7,1),Saidas!A:A,"<="&EOMONTH(DATE(2026,7,1),0),Saidas!D:D,"Transporte"),0) -> 0 | F14: =IFERROR(SUMIFS(Saidas!F:F,Saidas!A:A,">="&DATE(2026,8,1),Saidas!A:A,"<="&EOMONTH(DATE(2026,8,1),0),Saidas!D:D,"Transporte"),0) -> 0 | G14: =IFERROR(SUMIFS(Saidas!F:F,Saidas!A:A,">="&DATE(2026,9,1),Saidas!A:A,"<="&EOMONTH(DATE(2026,9,1),0),Saidas!D:D,"Transporte"),0) -> 0 | H14: =IFERROR(SUMIFS(Saidas!F:F,Saidas!A:A,">="&DATE(2026,10,1),Saidas!A:A,"<="&EOMONTH(DATE(2026,10,1),0),Saidas!D:D,"Transporte"),0) -> 0 | I14: =IFERROR(SUMIFS(Saidas!F:F,Saidas!A:A,">="&DATE(2026,11,1),Saidas!A:A,"<="&EOMONTH(DATE(2026,11,1),0),Saidas!D:D,"Transporte"),0) -> 0 | J14: =IFERROR(SUMIFS(Saidas!F:F,Saidas!A:A,">="&DATE(2026,12,1),Saidas!A:A,"<="&EOMONTH(DATE(2026,12,1),0),Saidas!D:D,"Transporte"),0) -> 0 | K14: =SUM(B14:J14) -> 0
A15: Ferramentas / Software | B15: =IFERROR(SUMIFS(Saidas!F:F,Saidas!A:A,">="&DATE(2026,4,1),Saidas!A:A,"<="&EOMONTH(DATE(2026,4,1),0),Saidas!D:D,"Software"),0) -> 0 | C15: =IFERROR(SUMIFS(Saidas!F:F,Saidas!A:A,">="&DATE(2026,5,1),Saidas!A:A,"<="&EOMONTH(DATE(2026,5,1),0),Saidas!D:D,"Software"),0) -> 0 | D15: =IFERROR(SUMIFS(Saidas!F:F,Saidas!A:A,">="&DATE(2026,6,1),Saidas!A:A,"<="&EOMONTH(DATE(2026,6,1),0),Saidas!D:D,"Software"),0) -> 0 | E15: =IFERROR(SUMIFS(Saidas!F:F,Saidas!A:A,">="&DATE(2026,7,1),Saidas!A:A,"<="&EOMONTH(DATE(2026,7,1),0),Saidas!D:D,"Software"),0) -> 0 | F15: =IFERROR(SUMIFS(Saidas!F:F,Saidas!A:A,">="&DATE(2026,8,1),Saidas!A:A,"<="&EOMONTH(DATE(2026,8,1),0),Saidas!D:D,"Software"),0) -> 0 | G15: =IFERROR(SUMIFS(Saidas!F:F,Saidas!A:A,">="&DATE(2026,9,1),Saidas!A:A,"<="&EOMONTH(DATE(2026,9,1),0),Saidas!D:D,"Software"),0) -> 0 | H15: =IFERROR(SUMIFS(Saidas!F:F,Saidas!A:A,">="&DATE(2026,10,1),Saidas!A:A,"<="&EOMONTH(DATE(2026,10,1),0),Saidas!D:D,"Software"),0) -> 0 | I15: =IFERROR(SUMIFS(Saidas!F:F,Saidas!A:A,">="&DATE(2026,11,1),Saidas!A:A,"<="&EOMONTH(DATE(2026,11,1),0),Saidas!D:D,"Software"),0) -> 0 | J15: =IFERROR(SUMIFS(Saidas!F:F,Saidas!A:A,">="&DATE(2026,12,1),Saidas!A:A,"<="&EOMONTH(DATE(2026,12,1),0),Saidas!D:D,"Software"),0) -> 0 | K15: =SUM(B15:J15) -> 0
A16: Outras Despesas | B16: =IFERROR(SUMIFS(Saidas!F:F,Saidas!A:A,">="&DATE(2026,4,1),Saidas!A:A,"<="&EOMONTH(DATE(2026,4,1),0),Saidas!D:D,"Outros"),0) -> 0 | C16: =IFERROR(SUMIFS(Saidas!F:F,Saidas!A:A,">="&DATE(2026,5,1),Saidas!A:A,"<="&EOMONTH(DATE(2026,5,1),0),Saidas!D:D,"Outros"),0) -> 0 | D16: =IFERROR(SUMIFS(Saidas!F:F,Saidas!A:A,">="&DATE(2026,6,1),Saidas!A:A,"<="&EOMONTH(DATE(2026,6,1),0),Saidas!D:D,"Outros"),0) -> 0 | E16: =IFERROR(SUMIFS(Saidas!F:F,Saidas!A:A,">="&DATE(2026,7,1),Saidas!A:A,"<="&EOMONTH(DATE(2026,7,1),0),Saidas!D:D,"Outros"),0) -> 0 | F16: =IFERROR(SUMIFS(Saidas!F:F,Saidas!A:A,">="&DATE(2026,8,1),Saidas!A:A,"<="&EOMONTH(DATE(2026,8,1),0),Saidas!D:D,"Outros"),0) -> 0 | G16: =IFERROR(SUMIFS(Saidas!F:F,Saidas!A:A,">="&DATE(2026,9,1),Saidas!A:A,"<="&EOMONTH(DATE(2026,9,1),0),Saidas!D:D,"Outros"),0) -> 0 | H16: =IFERROR(SUMIFS(Saidas!F:F,Saidas!A:A,">="&DATE(2026,10,1),Saidas!A:A,"<="&EOMONTH(DATE(2026,10,1),0),Saidas!D:D,"Outros"),0) -> 0 | I16: =IFERROR(SUMIFS(Saidas!F:F,Saidas!A:A,">="&DATE(2026,11,1),Saidas!A:A,"<="&EOMONTH(DATE(2026,11,1),0),Saidas!D:D,"Outros"),0) -> 0 | J16: =IFERROR(SUMIFS(Saidas!F:F,Saidas!A:A,">="&DATE(2026,12,1),Saidas!A:A,"<="&EOMONTH(DATE(2026,12,1),0),Saidas!D:D,"Outros"),0) -> 0 | K16: =SUM(B16:J16) -> 0
A17: (-) CUSTOS FIXOS MENSAIS | B17: =IFERROR('Custos Fixos'!B19,0) | C17: =IFERROR('Custos Fixos'!B19,0) | D17: =IFERROR('Custos Fixos'!B19,0) | E17: =IFERROR('Custos Fixos'!B19,0) | F17: =IFERROR('Custos Fixos'!B19,0) | G17: =IFERROR('Custos Fixos'!B19,0) | H17: =IFERROR('Custos Fixos'!B19,0) | I17: =IFERROR('Custos Fixos'!B19,0) | J17: =IFERROR('Custos Fixos'!B19,0) | K17: =IFERROR('Custos Fixos'!B19*9,0) -> 0
A18: (=) LUCRO OPERACIONAL EBITDA | B18: =IFERROR(B10-B11-B17,0) -> 10823.84 | C18: =IFERROR(C10-C11-C17,0) -> 20592.93 | D18: =IFERROR(D10-D11-D17,0) -> -970.67 | E18: =IFERROR(E10-E11-E17,0) -> 17571.92 | F18: =IFERROR(F10-F11-F17,0) -> 0 | G18: =IFERROR(G10-G11-G17,0) -> 0 | H18: =IFERROR(H10-H11-H17,0) -> 0 | I18: =IFERROR(I10-I11-I17,0) -> 0 | J18: =IFERROR(J10-J11-J17,0) -> 0 | K18: =SUM(B18:J18) -> 48018.02
A19: (-) Provisao IR / CSLL (% sobre EBITDA) | B19: =IFERROR(MAX(0,B18*'Custos Fixos'!B22),0) -> 0 | C19: =IFERROR(MAX(0,C18*'Custos Fixos'!B22),0) -> 0 | D19: =IFERROR(MAX(0,D18*'Custos Fixos'!B22),0) -> 0 | E19: =IFERROR(MAX(0,E18*'Custos Fixos'!B22),0) -> 0 | F19: =IFERROR(MAX(0,F18*'Custos Fixos'!B22),0) -> 0 | G19: =IFERROR(MAX(0,G18*'Custos Fixos'!B22),0) -> 0 | H19: =IFERROR(MAX(0,H18*'Custos Fixos'!B22),0) -> 0 | I19: =IFERROR(MAX(0,I18*'Custos Fixos'!B22),0) -> 0 | J19: =IFERROR(MAX(0,J18*'Custos Fixos'!B22),0) -> 0 | K19: =SUM(B19:J19) -> 0
A20: (=) LUCRO LIQUIDO | B20: =IFERROR(B18-B19,0) -> 10823.84 | C20: =IFERROR(C18-C19,0) -> 20592.93 | D20: =IFERROR(D18-D19,0) -> -970.67 | E20: =IFERROR(E18-E19,0) -> 17571.92 | F20: =IFERROR(F18-F19,0) -> 0 | G20: =IFERROR(G18-G19,0) -> 0 | H20: =IFERROR(H18-H19,0) -> 0 | I20: =IFERROR(I18-I19,0) -> 0 | J20: =IFERROR(J18-J19,0) -> 0 | K20: =SUM(B20:J20) -> 48018.02
A21: Margem Liquida (%) | B21: =IFERROR(B20/B5,0) -> 0.69622045 | C21: =IFERROR(C20/C5,0) -> 0.30661155 | D21: =IFERROR(D20/D5,0) -> -0.017398388 | E21: =IFERROR(E20/E5,0) -> 0.18495014 | F21: =IFERROR(F20/F5,0) -> 0 | G21: =IFERROR(G20/G5,0) -> 0 | H21: =IFERROR(H20/H5,0) -> 0 | I21: =IFERROR(I20/I5,0) -> 0 | ... K21: =IFERROR(K20/K5,0) -> 0.20563647

Sheet Contas a Pagar
A1: CONTAS A PAGAR — COMPROMISSOS E VENCIMENTOS FUTUROS
A2: Quando pagar, mude para Pago e registre tambem na aba Saidas.
A3: Descricao | B3: Fornecedor / Para quem | C3: Categoria | D3: Valor (R$) | E3: Vencimento | F3: Forma Pgto | G3: Situacao | H3: Data Pgto | I3: Observacoes
A4: TOTAL PENDENTE | D4: =IFERROR(SUMIF(G5:G24,"Pendente",D5:D24)+SUMIF(G5:G24,"Atrasado",D5:D24),0) -> 35167.53
A5: Repasse — Vista di Mari 1303 | B5: Soraya | C5: Comissão | D5: 5923.32 | E5: 46130 | F5: Pix | G5: PAGO | H5: 46130
A6: Repasse — Vista di Mari 1213 | B6: Soraya | C6: Comissão | D6: 6521.86 | E6: 46135 | F6: Pix | G6: PAGO | H6: 46135
A7: Repasse — MLar Kennedy 1106 | B7: André | C7: Comissão | D7: 6648.8 | E7: 46051 | F7: Pix | G7: PAGO | H7: 46051
A8: Repasse — Bônus | B8: André | C8: Comissão | D8: 2237.75 | E8: 46235 | F8: Pix | G8: PENDENTE | H8: 46260
A9: Repasse — MLar Cambeba 1104 | B9: André | C9: Comissão | D9: 6262.2 | E9: 46203 | F9: Pix | G9: PENDENTE | H9: 46260
A10: Repasse — MLar Cambeba 905 | B10: André | C10: Comissão | D10: 6219.34 | E10: 46203 | F10: Pix | G10: PENDENTE | H10: 46260
A11: Repasse — MLar Cambeba 705 | B11: Lucas | C11: Comissão | D11: 6486.58 | E11: 46235 | F11: Pix | G11: PAGO | H11: 46235 | I11: Conferir: data de pgto é futura (01/08) — checar se já saiu ou é erro de digitação
A12: Repasse — MLar Jacarey 808 | B12: Reno | C12: Comissão | D12: 6752.9 | E12: 46203 | F12: Pix | G12: PAGO | H12: 46203
A13: Repasse — Bella Aldeota 601 | B13: Reno | C13: Comissão | D13: 9763.1 | E13: 46210 | F13: Pix | G13: PAGO | H13: 46210
A14: Repasse — Bella Aldeota 1306 | B14: Reno | C14: Comissão | D14: 8485.59 | E14: 46265 | F14: Pix | G14: PENDENTE | H14: 46265
A15: Repasse — Bella Aldeota 1307 | B15: Angélica | C15: Comissão | D15: 500 | E15: 46265 | F15: Pix | G15: PENDENTE | H15: 46265
A16: Repasse — Maré/Marquise (Beatriz) | B16: Reno | C16: Comissão | D16: 13623.4 | E16: 46157 | F16: Pix | G16: PAGO | H16: 46157
A17: Repasse — Vibe Meireles 2103 | B17: Reno | C17: Comissão | D17: 11137.22 | E17: 46147 | F17: Pix | G17: PAGO | H17: 46147
A18: Repasse — Bella Aldeota (Mateus) | B18: Reno | C18: Comissão | D18: 10800.53 | E18: 46173 | F18: Pix | G18: PAGO | H18: 46173 | I18: Parcela 1/2
A19: Repasse — Bella Aldeota (Mateus) | B19: Reno | C19: Comissão | D19: 10800.53 | E19: 46217 | F19: Pix | G19: PAGO | H19: 46217 | I19: Parcela 2/2
A20: Repasse — Bella Aldeota Bônus (Mateus) | B20: Reno | C20: Comissão | D20: 1495 | E20: 46173 | F20: Pix | G20: PAGO | H20: 46173
A21: Repasse — MLar Kennedy | B21: Reno | C21: Comissão | D21: 7466.78 | E21: 46192 | F21: Pix | G21: PAGO | H21: 46192
A22: Repasse — Maré/Marquise (Gilson) | B22: Reno | C22: Comissão | D22: 13675.72 | E22: 46203 | F22: Pix | G22: PAGO | H22: 46203
A23: Repasse — Bella Aldeota 603 (José Jaime) | B23: Reno | C23: Comissão | D23: 8742.75 | E23: 46217 | F23: Pix | G23: PAGO | H23: 46217
A24: Repasse — Enjoy 1201 (Mara Tailane) | B24: Soraya | C24: Comissão | D24: 11462.65 | E24: 46260 | F24: Pix | G24: PENDENTE | H24: 46260
A25: Repasse — Enjoy 1201 (Mara Tailane) | B25: Angélica | C25: Comissão | D25: 500 | E25: 46260 | F25: Pix | G25: PENDENTE | H25: 46260
A26: Para adicionar: preencha nas linhas acima do TOTAL. Situacao: Pendente | Pago | Atrasado

Sheet Contas a Receber
A1: CONTAS A RECEBER — PARCELAS E VALORES PENDENTES
A2: Quando receber: mude para Recebido e registre tambem na aba Entradas.
A3: Descricao | B3: Cliente | C3: Valor Total (R$) | D3: Parcela | E3: Vencimento | F3: Situacao | G3: Data Recebimento | H3: Observacoes
A4: Comissão Soraya — Vista di Mari 1303 | B4: Nonato Gabriel Figueira | C4: 2961.23 | D4: 1/1 | E4: 46130 | F4: Recebido | G4: 46130 | H4: Corretor: Soraya
A5: Comissão Soraya — Vista di Mari 1213 | B5: Clemilton Lima de Souza | C5: 3260.96 | D5: 1/1 | E5: 46135 | F5: Recebido | G5: 46135 | H5: Corretor: Soraya
A6: Comissão André — MLar Kennedy Bônus R$5.000 | B6: Lucirene Souza | C6: 2237.75 | D6: 1/1 | E6: 46203 | F6: Pendente | H6: Corretor: André
A7: Comissão André — MLar Kennedy 1106 | B7: Lucirene Souza | C7: 6648.8 | D7: 1/1 | E7: 46051 | F7: Recebido | G7: 46051 | H7: Corretor: André
A8: Comissão André — Bônus | B8: Lucirene Souza | C8: 2500 | D8: 1/1 | E8: 46235 | F8: Pendente | H8: Corretor: André
A9: Comissão André — MLar Cambeba 1104 | B9: Luana | C9: 6262.2 | D9: 1/1 | E9: 46203 | F9: Pendente | H9: Corretor: André
A10: Comissão André — MLar Cambeba 905 | B10: Vinicius | C10: 6219.34 | D10: 1/1 | E10: 46203 | F10: Pendente | H10: Corretor: André
A11: Comissão Lucas — MLar Cambeba 705 | B11: Juliana Pontes | C11: 4324.38 | D11: 1/1 | E11: 46235 | F11: Recebido | G11: 46235 | H11: Corretor: Lucas. Conferir: data de receb. é futura (01/08) — checar se já entrou ou é erro de digitação
A12: Comissão Reno — MLar Jacarey 808 | B12: Rafael Hermínio | C12: 6752.9 | D12: 1/1 | E12: 46203 | F12: Recebido | G12: 46203 | H12: Corretor: Reno
A13: Comissão Reno — Bella Aldeota 601 | B13: Rafael Ditolvo | C13: 9763.1 | D13: 1/1 | E13: 46210 | F13: Recebido | G13: 46210 | H13: Corretor: Reno
A14: Comissão Reno — Bella Aldeota 1306 | B14: Marcio Anderson | C14: 16971.18 | D14: 1/1 | E14: 46234 | F14: Pendente | H14: Corretor: Reno
A15: Comissão Reno — Maré/Marquise | B15: Beatriz Dias | C15: 13623.4 | D15: 1/1 | E15: 46157 | F15: Recebido | G15: 46157 | H15: Corretor: Reno
A16: Comissão Reno — Vibe Meireles 2103 | B16: Sávio Santanta | C16: 11137.22 | D16: 1/1 | E16: 46147 | F16: Recebido | G16: 46147 | H16: Corretor: Reno
A17: Comissão Reno — Bella Aldeota (Mateus) | B17: Mateus Jereissati | C17: 10800.53 | D17: 1/2 | E17: 46173 | F17: Recebido | G17: 46173 | H17: Corretor: Reno
A18: Comissão Reno — Bella Aldeota (Mateus) | B18: Mateus Jereissati | C18: 10800.53 | D18: 2/2 | E18: 46217 | F18: Recebido | G18: 46217 | H18: Corretor: Reno
A19: Comissão Reno — Bella Aldeota Bônus (Mateus) | B19: Mateus Jereissati | C19: 1495 | D19: 1/1 | E19: 46173 | F19: Recebido | G19: 46173 | H19: Corretor: Reno
A20: Comissão Reno — MLar Kennedy | B20: Lia de Sousa Alexandre e Jonathan Silva Santos | C20: 7466.78 | D20: 1/1 | E20: 46192 | F20: Recebido | G20: 46192 | H20: Corretor: Reno
A21: Comissão Reno — Maré/Marquise | B21: Gilson Ferreira de Andrade | C21: 13675.72 | D21: 1/1 | E21: 46203 | F21: Recebido | G21: 46203 | H21: Corretor: Reno
A22: Comissão Reno — Bella Aldeota 603 | B22: José Jaime do Nascimento | C22: 8742.75 | D22: 1/1 | E22: 46217 | F22: Recebido | G22: 46217 | H22: Corretor: Reno
A23: Comissão Reno — Enjoy 1201 | B23: Mara Tailane Moreira da Silva | C23: 11462.65 | D23: 1/1 | E23: 46260 | F23: Pendente | H23: Corretor: Reno
A24: TOTAL PENDENTE | C24: =IFERROR(SUMIF(F4:F23,"Pendente",C4:C23),0) -> 45653.12
A26: Situacao: Pendente | Recebido | Atrasado. Total mostra apenas valores pendentes.

Sheet Custos Fixos
A1: CUSTOS FIXOS MENSAIS — CONFIGURACOES
A2: Despesas que se repetem todo mes. Atualize os valores quando os contratos mudarem.
A3: Descricao | B3: Valor Mensal (R$) | C3: Valor Anual (R$) | D3: Vencimento (dia) | E3: Categoria | F3: Observacoes
A4: VPS Hostinger | B4: 94.91 | C4: =B4*12 -> 1138.92 | D4: 1 | E4: Infraestrutura Web | F4: Mensalidade servidor
A5: Pagamento Mensal Angélica | B5: 2500 | C5: =B5*12 -> 30000 | D5: 5 | E5: Pessoal | F5: Funcionária administrativa
A6: Mensalidade Zaia | B6: 250 | C6: =B6*12 -> 3000 | D6: 1 | E6: Software | F6: Plataforma Zaia
A7: TOTAL CUSTOS FIXOS / MES | B7: =SUM(B4:B6) -> 2844.91 | C7: =SUM(C4:C6) -> 34138.92
A9: CONFIGURACOES DE IMPOSTO (usadas no DRE automaticamente)
A10: Aliquota ISS / Simples (% da receita bruta) | B10: 0.0356 | C10: Altere se sua aliquota mudar — consulte o contador
A11: Provisao IR / CSLL (% sobre lucro operacional) | B11: 0.15 | C11: Estimativa — consulte sempre seu contador

Sheet Impostos
A1: CONTROLE DE IMPOSTOS — SIMPLES NACIONAL (DAS)
A2: Alíquota Simples Nacional: 3,53% | Vencimento: todo dia 20 do mês seguinte ao recebimento
A4: ALÍQUOTA SIMPLES NACIONAL (editável) | B4: 0.0353 | D4: Altere o valor em B4 se sua alíquota mudar. Todos os cálculos atualizam automaticamente.
A6: DAS MENSAL — QUANTO PAGAR TODO DIA 20
A7: Mês de Recebimento | B7: Valor Bruto Recebido | C7: Alíquota Simples | D7: DAS a Pagar | E7: Vencimento (dia 20) | F7: Situação
A8: Janeiro/26 | B8: 14855.99 | C8: =B4 -> 0.0353 | D8: =B8*$B$4 -> 524.41645 | E8: 20/02/2026 | F8: Pago
A9: Março/26 | B9: 14101.26 | C9: =B4 -> 0.0353 | D9: =B9*$B$4 -> 497.77448 | E9: 20/04/2026 | F9: Pago
A10: Abril/26 | B10: 20811.21 | C10: =B4 -> 0.0353 | D10: =B10*$B$4 -> 734.63571 | E10: 20/05/2026 | F10: Pago
A11: Maio/26 (estimado) | B11: ← preencha com o valor bruto recebido no mês | C11: = | D11: =IF(ISNUMBER(B11),B11*$B$4,0) -> 0 | E11: 20/06/2026 | F11: Pendente
A12: Junho/26 (estimado) | B12: ← preencha com o valor bruto recebido no mês | C12: = | D12: =IF(ISNUMBER(B12),B12*$B$4,0) -> 0 | E12: 20/07/2026 | F12: Pendente
A14: IMPOSTO POR COMISSÃO RECEBIDA — QUANTO CADA VENDA GERA DE DAS
A15: Corretor | B15: Cliente / Empreendimento | C15: Data Recebimento | D15: Valor Bruto (comissão) | E15: Retido (10,49%) | F15: Líquido Recebido | G15: Simples (3,53%) | H15: Diferença | I15: Status
A16: Soraya | B16: Vista di Mari 1303 — Nonato | C16: 46130 | D16: 8919.09 | E16: 935.61254 | F16: 8915 | G16: 314.84388 | H16: 620.76866 | I16: Recebido
A17: Soraya | B17: Vista di Mari 1213 — Clemilton | C17: 46135 | D17: 11892.12 | E17: 2109.6621 | F17: 9782.82 | G17: 419.79184 | H17: 1689.8703 | I17: Recebido
A18: André | B18: MLar Kennedy Bônus — Lucirene | C18: 46172 | D18: 5000 | E18: 524.5 | F18: 4475.5 | G18: 176.5 | H18: 348 | I18: Pendente
A19: André | B19: MLar Kennedy 1106 — Lucirene | C19: 46051 | D19: 14855.99 | E19: 1558.3934 | F19: 13297.6 | G19: 524.41645 | H19: 1033.9769 | I19: Recebido
A20: André | B20: MLar Cambeba 1104 — Luana | C20: 46172 | D20: 13992.17 | E20: 1467.7786 | F20: 12524.39 | G20: 493.9236 | H20: 973.85503 | I20: Pendente
A21: André | B21: MLar Cambeba 905 — Vinicius | C21: 46172 | D21: 13896.42 | E21: 1457.7345 | F21: 12438.69 | G21: 490.54363 | H21: 967.19083 | I21: Pendente
A22: Lucas | B22: MLar Cambeba 705 — Juliana Pontes | C22: 46129 | D22: 14101.26 | E22: 1128.1008 | F22: 12973.16 | G22: 497.77448 | H22: 630.32632 | I22: Recebido
A23: Reno | B23: MLar Jacarey 808 — Rafael H. | C23: 46172 | D23: 14000 | E23: 1468.6 | F23: 12531.4 | G23: 494.2 | H23: 974.4 | I23: Pendente
A24: Reno | B24: Bella Aldeota 601 — Rafael D. | C24: 46172 | D24: 20240.69 | E24: 2123.2484 | F24: 18117.44 | G24: 714.49636 | H24: 1408.752 | I24: Pendente
A25: Reno | B25: Bella Aldeota 1306 — Marcio A. | C25: 46172 | D25: 18960.09 | E25: 1988.9134 | F25: 16971.18 | G25: 669.29118 | H25: 1319.6223 | I25: Pendente
A26: Reno | B26: Maré Marquise — Beatriz Dias | C26: 46157 | D26: 30439.94 | E26: 3193.1497 | F26: 27246.79 | G26: 1074.5299 | H26: 2118.6198 | I26: Pendente
A27: Reno | B27: Vibe Meireles — Sávio S. | C27: 46150 | D27: 24884.86 | E27: 2610.4218 | F27: 22274.44 | G27: 878.43556 | H27: 1731.9863 | I27: Pendente
A28: Reno | B28: Bella Aldeota — Mateus Jereissati | C28: 46173 | D28: 22391.48 | E28: 790.41924 | F28: 21601.06 | G28: 790.41924 | H28: 0 | I28: Pendente
A29: TOTAIS | D29: =SUM(D16:D28) -> 213574.11 | E29: =SUM(E16:E28) -> 21356.534 | F29: =SUM(F16:F28) -> 193149.47 | G29: =SUM(G16:G28) -> 7539.1661 | H29: =SUM(H16:H28) -> 13817.368
A31: ⚠ ATENÇÃO: A coluna Diferença mostra o quanto a construtora reteve a MAIS que o seu Simples. Valores positivos indicam possível crédito tributário — consulte seu contador urgente!
A32: O Simples Nacional (DAS) vence todo dia 20 do mês seguinte. Ex: comissão recebida em maio → DAS pago até 20/junho.

Sheet Guia de Uso
A1: GUIA DE USO — COMO USAR ESTA PLANILHA
A2: Rotina: recebeu → Entradas | gastou → Saidas | parcela futura → Contas a Receber
A3: Dashboard | B3: Visao geral automatica. Nao edite — calculado pelas outras abas.
A4: DRE | B4: Resultado mensal: receita menos despesas menos custos fixos igual lucro. Atualiza sozinho.
A5: Entradas | B5: Registre TODA receita: comissoes, reembolsos, outras. Preencha sempre a Categoria.
A6: Saidas | B6: Registre TODA despesa variavel. Marque Pago? como Sim quando confirmado.
A7: Custos Fixos | B7: Liste despesas mensais recorrentes. Atualize quando contratos mudarem.
A8: Contas a Receber | B8: Parcelas futuras. Quando receber, mude para Recebido e registre em Entradas.
A9: Impostos | B9: Configure aliquota em Custos Fixos (B22 e B23). Consulte seu contador.
A10: Celulas amarelas | B10: Celulas amarelas = voce preenche. Celulas brancas com formulas = nao edite.
A11: Categorias | B11: Use sempre a mesma grafia. Ex: Marketing (nao Mkt, nao marketing).
